PrimeBot/__init__.py
PrimeBot/B2E/__init__.py
PrimeBot/Cnab750/__init__.py
PrimeBot/CpfCnpj/__init__.py
PrimeBot/CpfCnpj/api_codes.py
PrimeBot/CpfCnpj/model.py
PrimeBot/D4Sign/__init__.py
PrimeBot/DeathByCaptcha/__init__.py
PrimeBot/Documents/__init__.py
PrimeBot/Elastic/__init__.py
PrimeBot/EmailAlert/__init__.py
PrimeBot/ExchangeGraph/__init__.py
PrimeBot/FeriadosBancarios/__init__.py
PrimeBot/FeriadosBancarios/model.py
PrimeBot/IntegracaoSendGrid/__init__.py
PrimeBot/ListenerECS/__init__.py
PrimeBot/Mongo/__init__.py
PrimeBot/OracleDB/__init__.py
PrimeBot/Vault/__init__.py
PrimeBotFramework-1.0.62.dist-info/METADATA
PrimeBotFramework-1.0.62.dist-info/WHEEL
PrimeBotFramework-1.0.62.dist-info/top_level.txt
PrimeBotFramework-1.0.62.dist-info/RECORD
