Metadata-Version: 2.1
Name: PrimeBotFramework
Version: 1.0.62
Summary: Um pacote de padronizacao de pacotes a serem utilizados pela Prime
Home-page: 
Author: Prime Control
Author-email: 
License: MIT
Keywords: PrimeBotFramework
Classifier: Development Status :: 5 - Production/Stable
Classifier: Intended Audience :: Education
Classifier: Operating System :: Microsoft :: Windows :: Windows 10
Classifier: License :: OSI Approved :: MIT License
Classifier: Programming Language :: Python :: 3
Requires-Python: ~=3.8
Requires-Dist: hvac ==1.0.2
Requires-Dist: mongoengine ==0.22.1
Requires-Dist: elasticsearch-dsl ==7.3.0
Requires-Dist: dateUts ==0.1.0
Requires-Dist: ecs-logging
Requires-Dist: datetime
Requires-Dist: requests >=2.28.1
Requires-Dist: pyaml >=21.10.1
Requires-Dist: pydantic >=1.10.2
Requires-Dist: cx-Oracle ==8.3.0
Requires-Dist: sendgrid ==6.10.0
Requires-Dist: certifi ==2022.12.7
